cluster_detection/__init__.py
cluster_detection/blob_detection.py
cluster_detection/clustering_methods.py
cluster_detection/parameter_template.py
cluster_detection/utils.py
cluster_detection/find_optimal_param/__init__.py
cluster_detection/find_optimal_param/dop.py
cluster_detection/reconstruction/__init__.py
cluster_detection/reconstruction/recon.py
cluster_detection-0.2.2.dist-info/METADATA
cluster_detection-0.2.2.dist-info/WHEEL
cluster_detection-0.2.2.dist-info/RECORD
