Metadata-Version: 2.4
Name: cluster-detection
Version: 0.2.2
Summary: Cluster Detection in Microscopy Images
Requires-Python: ==3.10.13
Requires-Dist: lmfit>=1.0.2
Requires-Dist: matplotlib>=3.6.0
Requires-Dist: mkdocs==1.6.0
Requires-Dist: numpy>=1.21.2
Requires-Dist: pandas>=2.2.3
Requires-Dist: scikit-image>=0.18.3
Requires-Dist: scikit-learn>=1.5.2
Requires-Dist: scipy>=1.7.1
